suanpan/__init__.py
suanpan/abqfil.py
suanpan/ftnfil.py
suanpan_abaqus-0.1.0.dist-info/METADATA
suanpan_abaqus-0.1.0.dist-info/WHEEL
suanpan_abaqus-0.1.0.dist-info/RECORD
