Metadata-Version: 2.4
Name: suanpan-abaqus
Version: 0.1.0
Summary: Python interface to Abaqus .fil files
Author-email: Stefano Miccoli <stefano.miccoli@polimi.it>
License-Expression: MIT
Classifier: Development Status :: 3 - Alpha
Classifier: Environment :: Other Environment
Classifier: Intended Audience :: Developers
Classifier: Programming Language :: Python
Classifier: Programming Language :: Python :: 3
Classifier: Programming Language :: Python :: 3.10
Requires-Python: >=3.10
Requires-Dist: numpy>=1.21.2
